MANIFEST.in
requirements.txt
setup.cfg
setup.py
test_requirements.txt
erc20_faucet/__init__.py
erc20_faucet/faucet.py
erc20_faucet/interface.py
erc20_faucet.egg-info/PKG-INFO
erc20_faucet.egg-info/SOURCES.txt
erc20_faucet.egg-info/dependency_links.txt
erc20_faucet.egg-info/entry_points.txt
erc20_faucet.egg-info/requires.txt
erc20_faucet.egg-info/top_level.txt
erc20_faucet/data/ERC20Faucet.bin
erc20_faucet/data/ERC20Faucet.json
erc20_faucet/data/ERC20Faucet.metadata.json
erc20_faucet/data/ERC20FaucetStorage.bin
erc20_faucet/data/ERC20FaucetStorage.json
erc20_faucet/data/ERC20FaucetStorage.metadata.json
erc20_faucet/data/ERC20SingleShotFaucet.bin
erc20_faucet/data/ERC20SingleShotFaucet.json
erc20_faucet/data/ERC20SingleShotFaucetStorage.bin
erc20_faucet/data/ERC20SingleShotFaucetStorage.json
erc20_faucet/data/IERC20SingleShotFaucet.json
erc20_faucet/data/IERC20SingleShotFaucetStorage.json
erc20_faucet/runnable/gift.py
erc20_faucet/runnable/list.py
erc20_faucet/runnable/publish.py
tests/test_basic.py