Metadata-Version: 2.1
Name: erc20-faucet
Version: 0.8.0
Summary: ERC20 token faucet
Home-page: https://gitlab.com/cicnet/erc20-faucet
Author: Louis Holbrook
Author-email: dev@holbrook.no
License: AGPLv3+
Keywords: ethereum
Classifier: Programming Language :: Python :: 3
Classifier: Operating System :: OS Independent
Classifier: Development Status :: 4 - Beta
Classifier: Environment :: Console
Classifier: Intended Audience :: Developers
Classifier: License :: OSI Approved :: GNU Affero General Public License v3 or later (AGPLv3+)
Classifier: Topic :: Internet
Classifier: Topic :: Software Development :: Libraries
Requires-Python: >=3.8
Provides-Extra: testing
